MANIFEST.in
README.md
setup.py
xprintidle.py
__pycache__/_xprintidle_cffi_87c92e52x21f04958.c
__pycache__/_xprintidle_cffi_c01bf5b3xc5a90381.c
src/xprintidle.c
xprintidle.egg-info/PKG-INFO
xprintidle.egg-info/SOURCES.txt
xprintidle.egg-info/dependency_links.txt
xprintidle.egg-info/not-zip-safe
xprintidle.egg-info/requires.txt
xprintidle.egg-info/top_level.txt