Metadata-Version: 1.0
Name: xprintidle
Version: 0.2
Summary: A cffi wrapper around xprintidle.
Home-page: https://github.com/dpnova/python-xprintidle
Author: David P. Novakovic
Author-email: davidnovakovic@gmail.com
License: UNKNOWN
Platform: UNKNOWN
